spacelock/__init__.py
spacelock/__main__.py
spacelock/core.py
spacelock/settings.py
spacelock-0.0.2.dist-info/LICENSE
spacelock-0.0.2.dist-info/WHEEL
spacelock-0.0.2.dist-info/METADATA
spacelock-0.0.2.dist-info/RECORD
