Metadata-Version: 2.1
Name: spacelock
Version: 0.0.2
Summary: Author:     LanHao
Home-page: https://github.com/bigpangl/spacelock
Author: LHao
Author-email: bigpangl@163.com
Classifier: License :: OSI Approved :: MIT License
Requires-Dist: rtree
Requires-Dist: sortedcontainers
Requires-Dist: dynaconf
